logwrap/__init__.py
logwrap/_version.py
logwrap/constants.py
logwrap/log_on_access.py
logwrap/log_wrap.py
logwrap/py.typed
logwrap/repr_utils.py
logwrap-11.1.1.dist-info/LICENSE
logwrap-11.1.1.dist-info/METADATA
logwrap-11.1.1.dist-info/WHEEL
logwrap-11.1.1.dist-info/top_level.txt
logwrap-11.1.1.dist-info/RECORD
