Metadata-Version: 2.1
Name: logwrap
Version: 11.1.1
Summary: Decorator for logging function arguments and return value by human-readable way
Home-page: https://github.com/python-useful-helpers/logwrap
Author-email: Aleksei Stepanov <penguinolog@gmail.com>
Maintainer-email: Aleksei Stepanov <penguinolog@gmail.com>, Antonio Esposito <esposito.cloud@gmail.com>, Dennis Dmitriev <dis-xcom@gmail.com>
License: Apache-2.0
Project-URL: Documentation, https://logwrap.readthedocs.io/
Project-URL: Repository, https://github.com/python-useful-helpers/logwrap
Project-URL: Bug Tracker, https://github.com/python-useful-helpers/logwrap/issues
Keywords: logging,debugging,development
Classifier: Development Status :: 5 - Production/Stable
Classifier: Intended Audience :: Developers
Classifier: Topic :: Software Development :: Libraries :: Python Modules
Classifier: License :: OSI Approved :: Apache Software License
Classifier: Programming Language :: Python :: 3
Classifier: Programming Language :: Python :: 3 :: Only
Classifier: Programming Language :: Python :: 3.8
Classifier: Programming Language :: Python :: 3.9
Classifier: Programming Language :: Python :: 3.10
Classifier: Programming Language :: Python :: 3.11
Classifier: Programming Language :: Python :: 3.12
Classifier: Programming Language :: Python :: Implementation :: CPython
Classifier: Programming Language :: Python :: Implementation :: PyPy
Requires-Python: >=3.8.0
License-File: LICENSE
